visio_library/__init__.py
visio_library/visio_utils.py
visio_library-0.1.1.dist-info/LICENSE
visio_library-0.1.1.dist-info/METADATA
visio_library-0.1.1.dist-info/WHEEL
visio_library-0.1.1.dist-info/top_level.txt
visio_library-0.1.1.dist-info/RECORD
