Metadata-Version: 2.1
Name: visio-library
Version: 0.1.1
Summary: A library to automate Visio operations.
Author: Yacine Gacem
Author-email: yacine.gacem@gmail.com
Classifier: Programming Language :: Python :: 3
Classifier: License :: OSI Approved :: MIT License
Classifier: Operating System :: OS Independent
Requires-Python: >=3.6
License-File: LICENSE
Requires-Dist: pywin32
